<?xml version="1.0" encoding="UTF-8" standalone="yes"?><!--Boris BBM: ONB--><set version="1.4"><pointSurvey embargo="OPENBAAR" version="1.4"><identification id="B34F1342"><remark>unieke identificatie</remark></identification><identification id="418/L-51    1952"><organisation>Commissie Onderzoek Landbouwwaterhuishouding Nederland</organisation></identification><surveyLocation><surveyLocationMethod code="LGPS">GPS (Global Positioning System)</surveyLocationMethod><coordinates UoM="METER" coordSystem="RD" originalMeasurement="JA"><coordinateX>253304</coordinateX><coordinateY>466107</coordinateY></coordinates><coordinates UoM="METER" coordSystem="WGS84-UTM31" originalMeasurement="NEE"><coordinateX>761475</coordinateX><coordinateY>5787327</coordinateY></coordinates></surveyLocation><surfaceElevation levelDay="29" levelMonth="3" levelYear="1976"><elevation UoM="CENTIMETER" levelReference="NAP" levelValue="2975" originalMeasurement="JA"/></surfaceElevation><geoPoliticalLocation><countryName>Nederland</countryName><stateOrProvinceName>Overijssel</stateOrProvinceName><map maptype="TOPO1961">34F</map></geoPoliticalLocation><borehole baseDepth="200" baseDepthUoM="CENTIMETER" version="1.4"><ownerOrg>TNO-NITG</ownerOrg><boreholePurpose>VKN-G</boreholePurpose><date startDay="14" startMonth="1" startYear="1972"/><lithoDescr embargo="OPENBAAR" gravelMedianUoM="MICROMETER" layerDepthReference="MV" layerDepthUoM="CENTIMETER" lithoDescrQualityAut="E" lithoDescrStandard="ONB" lithoDescrVersion="1" medianClassStandard="ONB" sandMedianUoM="MILLIMETER" version="1.4"><lithoInterval baseDepth="60" topDepth="0"><lithology code="Z">zand</lithology><colorMain code="BR">bruin</colorMain><colorIntensity code="DO">donker-</colorIntensity></lithoInterval><lithoInterval baseDepth="180" topDepth="60"><lithology code="Z">zand</lithology><colorMain code="BR">bruin</colorMain><colorSecondary code="TGE">geel-</colorSecondary></lithoInterval><lithoInterval baseDepth="200" topDepth="180"><lithology code="Z">zand</lithology><colorMain code="GR">grijs</colorMain></lithoInterval></lithoDescr></borehole></pointSurvey></set>